fzy/__about__.py
fzy/__init__.py
fzy/choices.cpython-35m-darwin.so
fzy/match.cpython-35m-darwin.so
fzy/search.py
fzypy-0.0.2.dist-info/LICENSE
fzypy-0.0.2.dist-info/METADATA
fzypy-0.0.2.dist-info/WHEEL
fzypy-0.0.2.dist-info/top_level.txt
fzypy-0.0.2.dist-info/RECORD
