Metadata-Version: 2.1
Name: fzypy
Version: 0.0.2
Summary: A fuzzy finder in Python based on fzy
Home-page: https://github.com/puilp0502/fzypy
Author: Frank Yang
Author-email: puilp0502@gmail.com
License: UNKNOWN
Platform: UNKNOWN
Classifier: Development Status :: 3 - Alpha
Classifier: License :: OSI Approved :: MIT License
Classifier: Operating System :: POSIX
Classifier: Programming Language :: Python :: 3
Requires-Python: >=3.5
